README.md
setup.py
decompose/__init__.py
decompose/sklearn.py
decompose/version.py
decompose.egg-info/PKG-INFO
decompose.egg-info/SOURCES.txt
decompose.egg-info/dependency_links.txt
decompose.egg-info/requires.txt
decompose.egg-info/top_level.txt
decompose/data/__init__.py
decompose/data/lowRank.py
decompose/distributions/__init__.py
decompose/distributions/algorithms.py
decompose/distributions/cenDoubleLomax.py
decompose/distributions/cenDoubleLomaxAlgorithms.py
decompose/distributions/cenLaplace.py
decompose/distributions/cenLaplaceAlgorithms.py
decompose/distributions/cenNnNormal.py
decompose/distributions/cenNnNormalAlgorithms.py
decompose/distributions/cenNnT.py
decompose/distributions/cenNnTAlgorithms.py
decompose/distributions/cenNormal.py
decompose/distributions/cenNormalAlgorithms.py
decompose/distributions/cenT.py
decompose/distributions/cenTAlgorithms.py
decompose/distributions/chopin2011.py
decompose/distributions/distribution.py
decompose/distributions/exponential.py
decompose/distributions/exponentialAlgorithms.py
decompose/distributions/jumpNormal.py
decompose/distributions/jumpNormalAlgorithms.py
decompose/distributions/laplace.py
decompose/distributions/laplaceAlgorithms.py
decompose/distributions/lomax.py
decompose/distributions/lomaxAlgorithms.py
decompose/distributions/nnNormal.py
decompose/distributions/nnNormalAlgorithms.py
decompose/distributions/nnUniform.py
decompose/distributions/nnUniformAlgorithms.py
decompose/distributions/normal.py
decompose/distributions/normalAlgorithms.py
decompose/distributions/normalExponential.py
decompose/distributions/normalLaplace.py
decompose/distributions/normalNnNormal.py
decompose/distributions/normalNnUniform.py
decompose/distributions/normalNormal.py
decompose/distributions/normalUniform.py
decompose/distributions/product.py
decompose/distributions/productDistLookup.py
decompose/distributions/t.py
decompose/distributions/tAlgorithms.py
decompose/distributions/tfppf.py
decompose/distributions/trnorm.py
decompose/distributions/uniform.py
decompose/distributions/uniformAlgorithms.py
decompose/distributions/tests/__init__.py
